cmdappinterface/__init__.py
cmdappinterface-0.0.2.dist-info/licenses/LICENSE
cmdappinterface-0.0.2.dist-info/METADATA
cmdappinterface-0.0.2.dist-info/WHEEL
cmdappinterface-0.0.2.dist-info/top_level.txt
cmdappinterface-0.0.2.dist-info/RECORD
