Metadata-Version: 2.4
Name: cmdappinterface
Version: 0.0.2
Summary: A small tool for building Python interfaces inside a terminal.
Author-email: alejandro-vaz <alejandro.vaz.myt@gmail.com>
License: MIT License
Classifier: Programming Language :: Python :: 3
Classifier: License :: OSI Approved :: MIT License
Classifier: Operating System :: OS Independent
Requires-Python: >=3.7
License-File: LICENSE
Dynamic: license-file
